{
	"authors": [
		"Ferhat Kurtulmuş"
	],
	"copyright": "Copyright © 2022, Ferhat Kurtulmuş",
	"dependencies": {
		"dcompute": {"repository": "git+https://github.com/aferust/dcompute.git", "version": "~master"},
        "mir-algorithm": ">=3.15.3",
        "dcv:core": {"repository": "git+https://github.com/libmir/dcv.git", "version": "~master"},
        "dcv:imageio": {"repository": "git+https://github.com/libmir/dcv.git", "version": "~master"},
        "dcv:plot": {"repository": "git+https://github.com/libmir/dcv.git", "version": "~master"},
        "derelict-cuda": "*"
	},
	"description": "stereoDisparity - Stereo Disparity Computation with dlang, dcompute (CUDA backend)",
	"license": "BSL-1.0",
	"name": "stereo",
    "comment-dflags": ["-output-ll"],
    "commdflags": ["-vv"]
}